{
  "9bc92ee306f6ff90": ["bp___systeminit", "__SystemInit(v) — FLIRT-identified"],
  "fd9186e16517dde6": ["bp_halt", "Halt(ExitCode) — terminate program"],
  "d54dc076ebfc9998": ["bp_printstring", "Print string to stdout"],
  "b79c2c2d9afb49e2": ["bp_readtext", "ReadText — system runtime function"],
  "74e1112e20c85507": ["bp_writeblanks", "WriteBlanks — system runtime function"],
  "58f8e8bb8520edc7": ["bp_writebuffer", "WriteBuffer — system runtime function"],
  "22b4932a4e08a93e": ["bp_readln", "ReadLn(Text) — read line from text file"],
  "f2374359ffdb3a56": ["bp_writeln", "WriteLn(Text) — write newline"],
  "b07c2f3457243279": ["bp_write", "Write(m4Text) — FLIRT-identified"],
  "e37d6e58e2016eaa": ["bp_inoutproc", "I/O procedure dispatcher"],
  "9d1e6a0338b704c9": ["bp_read_char", "Read(Text, Char) — read character"],
  "fdf5c26cb87d24d7": ["bp_write_char", "Write(Text, Char, Word) — write char with field width"],
  "5fbf833bf53bd7b5": ["bp_read_longint", "Read(Text, Longint) — read longint"],
  "a29913392603bb8c": ["bp_write_longint", "Write(Text, Longint, Word) — write longint with width"],
  "79b675b112d976c6": ["bp_int2str", "Int2Str — system runtime function"],
  "c4b3cf726f551bfa": ["bp_str2int", "Str2Int — system runtime function"],
  "a1dc4e1fc5fffca1": ["bp_clear_dseg", "Clear data segment (BSS init)"],
  "a427b3aae6d7abef": ["crt_gotoxy", "GotoXY(Byte, Byte) — position cursor"],
  "08187e9e4e0d0469": ["crt_wherex", "WhereX — current cursor column"],
  "3f872ab6b0d3c87d": ["crt_wherey", "WhereY — current cursor row"],
  "0c108847fe580c13": ["crt_textcolor", "TextColor(Color) — set foreground"],
  "f3abaf388697fc06": ["crt_textbg", "TextBackground(Color) — set background"],
  "cdbfc4a010d12e37": ["crt_delay", "Delay(MS) — millisecond pause"],
  "8e81009f7f7bc256": ["crt_sound", "Sound(Hz) — start speaker tone"],
  "f05af9f438d1a276": ["crt_nosound", "NoSound — stop speaker"],
  "cad72eb6918c3706": ["crt_readkey", "ReadKey — read character from keyboard"],
  "6d8d6b9ffaaa6568": ["crt_assigncrt", "AssignCrt(Text) — assign text to CRT"],
  "9821f48e715c6178": ["crt_textmode", "TextMode(Mode) — set text video mode"],
  "f9d8ee02e4a6f0c7": ["bp_window", "Window(4Bytet1t1t1) — FLIRT-identified"],
  "5fc6a008b9c8e259": ["crt_clrscr", "ClrScr — clear screen"],
  "9514298b857c6b6a": ["bp_clreol", "ClrEol(v) — FLIRT-identified"],
  "f488156eed89bfe3": ["crt_keypressed", "KeyPressed — check if key available"],
  "262c295f4c07e532": ["bp_getintvec", "GetIntVec(4Bytem7Pointer) — FLIRT-identified"],
  "73e3b6ca4372c04a": ["bp_setintvec", "SetIntVec(4Byte7Pointer) — FLIRT-identified"],
  "fea1a79dfd8199c5": ["bp_fsplit", "FSplit(7PathStrm6DirStrm7NameStrm6ExtStr) — FLIRT-identified"],
  "1ec834e66b65daf5": ["bp_msdos", "MsDos(m9Registers) — FLIRT-identified"],
  "f9131138e5467a23": ["bp_intr", "Intr(4Bytem9Registers) — FLIRT-identified"],
  "9f4118d4c11f66e0": ["bp_getmem", "GetMem(Word) — allocate raw memory"],
  "c75f18c8b8a8458d": ["bp_freemem", "FreeMem(Ptr, Size) — free raw memory"],
  "c3081cd0259e9e48": ["bp_newmemory", "NewMemory — system runtime function"],
  "2405d5495e7cba63": ["bp_dismemory", "DisMemory — system runtime function"],
  "56ba0eb7f6f39012": ["bp___iocheck", "__IOCheck(v) — FLIRT-identified"],
  "a0a7ee54487a1dac": ["bp___stackcheck", "__StackCheck(4Word) — FLIRT-identified"],
  "366dbe1caa63c3dd": ["bp_read_str", "Read(Text, String, Word) — read string with max length"],
  "54e0350d2dfa22b8": ["bp_write_str", "Write(Text, String, Word) — write string to text file"],
  "f8c90fc8220d66d9": ["bp_paramstr", "ParamStr(m6String4Word) — FLIRT-identified"],
  "b8bb7d9c54cc2cd2": ["bp_paramcount", "ParamCount — number of command line args"],
  "384b396f3f136c1a": ["bp_str_assign", "String assignment"],
  "dea8e95a550229b0": ["bp_str_assign_n", "String assignment with max length"],
  "4d7c8db28db67e08": ["bp_copy", "Copy(String, String, Integer, Integer) — substring"],
  "58809b95b3af5a3b": ["bp_concat", "Concat(String, String) — string concatenation"],
  "c5b7fbad06d65787": ["bp_pos", "Pos(String, String) — find substring position"],
  "48a8349c85ad560a": ["bp__bsub", "_bsub(m6Stringt1) — FLIRT-identified"],
  "eff5541b7e60c2da": ["bp__basg", "_basg(m6String4Char) — FLIRT-identified"],
  "2baa167ff6bcf2e9": ["bp__basg", "_basg(m6Stringn4Char4Byte) — FLIRT-identified"],
  "7ee1c1712ad3fa6e": ["bp_insert", "Insert(String, String, Word, Integer) — insert substring"],
  "476d21a5fc4d6c40": ["bp_delete", "Delete(String, Integer, Integer) — delete substring"],
  "6d710a896b33bcb1": ["bp_realadd", "RealAdd — system runtime function"],
  "c87e3cb369ac29b7": ["bp_realmul", "RealMul — system runtime function"],
  "0244a88d87221d8a": ["bp_realdiv", "RealDiv — system runtime function"],
  "faa04152ae012f1b": ["bp_realcmp", "RealCmp — system runtime function"],
  "f7e567a417cb2750": ["bp_realfloat", "RealFloat — system runtime function"],
  "6d9884a8cb59517d": ["bp_realtrunc", "RealTrunc — system runtime function"],
  "8a878c4b9785f077": ["bp_real2str", "Real2Str — system runtime function"],
  "8b1eee9cff6bf47a": ["bp_str2real", "Str2Real — system runtime function"],
  "98cdef609005ac65": ["bp_str_long", "Str(Longint, Word, String, Byte) — longint to string"],
  "07628e9fc722bdbb": ["bp_val__longint", "Val__Longint(m6Stringm7Integer) — FLIRT-identified"],
  "82a34c500aaafd20": ["bp_str", "Str(4Real4Wordt2m6String4Word) — FLIRT-identified"],
  "669b62ff00cc3cc9": ["bp_val__real", "Val__Real(m6Stringm7Integer) — FLIRT-identified"],
  "39349f6a5d246b21": ["bp_move", "Move(m3Anyt14Word) — FLIRT-identified"],
  "b0849b5cfc1d0c7e": ["bp_upcase", "UpCase(Char) — convert to uppercase"],
  "54de4f059e4b4e91": ["dos_getdate", "GetDate(Word,Word,Word,Word)"],
  "dfe03b79b4763d60": ["bp_setdate", "SetDate(4Wordt1t1) — FLIRT-identified"],
  "4bb71198714d2f73": ["dos_gettime", "GetTime(Word,Word,Word,Word)"],
  "d226270ece8d49cd": ["bp_settime", "SetTime(4Wordt1t1t1) — FLIRT-identified"],
  "8f5592e98c052d98": ["dos_diskfree", "DiskFree(Drive) — free disk space"],
  "cab4aab7a36c0de7": ["dos_disksize", "DiskSize(Drive) — total disk size"],
  "996cf704dbba6658": ["dos_findfirst", "FindFirst(PathStr,Word,SearchRec)"],
  "03d195a625015bcd": ["dos_findnext", "FindNext(SR) — find next matching file"],
  "da9a4c33da31be70": ["dos_envcount", "EnvCount — number of environment strings"],
  "f11e4b7133abc00f": ["dos_envstr", "EnvStr(Index) — environment string by index"],
  "7779b581bf20f940": ["dos_getenv", "GetEnv(String) — get environment variable"],
  "d7e88b8a5e5ea983": ["bp_read", "Read(m4Text4Real) — FLIRT-identified"],
  "64492b499242e721": ["bp_write_real", "Write(Text, Real, Word, Word) — write real number"],
  "b7474eed9538115e": ["bp_erase", "Erase(File) — delete file"],
  "09615aa4736cd8a2": ["bp_filepos", "FilePos(File) — current position"],
  "1f81590fc2d9cf02": ["bp_filesize", "FileSize(File) — number of records"],
  "219d4e42a4065099": ["bp_eof", "Eof(File) — end of file check"],
  "c67c0a96b6d039d2": ["bp_random", "Random(Word) — random integer 0..N-1"],
  "791f9e15faaca636": ["bp_write_bool", "Write(Text, Boolean, Word) — write boolean with width"]
}
